chaperone-0.2.23.dist-info/entry_points.txt
chaperone-0.2.23.dist-info/DESCRIPTION.rst
chaperone-0.2.23.dist-info/WHEEL
chaperone-0.2.23.dist-info/metadata.json
chaperone-0.2.23.dist-info/top_level.txt
chaperone-0.2.23.dist-info/METADATA
chaperone-0.2.23.dist-info/RECORD
chaperone/__init__.py
chaperone/exec/envcp.py
chaperone/exec/chaperone.py
chaperone/exec/__init__.py
chaperone/exec/sdnotify.py
chaperone/exec/telchap.py
chaperone/cproc/process_manager.py
chaperone/cproc/version.py
chaperone/cproc/client.py
chaperone/cproc/commands.py
chaperone/cproc/subproc.py
chaperone/cproc/watcher.py
chaperone/cproc/__init__.py
chaperone/cproc/pt/forking.py
chaperone/cproc/pt/oneshot.py
chaperone/cproc/pt/simple.py
chaperone/cproc/pt/cron.py
chaperone/cproc/pt/notify.py
chaperone/cproc/pt/__init__.py
chaperone/cutil/proc.py
chaperone/cutil/syslog_info.py
chaperone/cutil/patches.py
chaperone/cutil/format.py
chaperone/cutil/logging.py
chaperone/cutil/syslog_handlers.py
chaperone/cutil/config.py
chaperone/cutil/misc.py
chaperone/cutil/errors.py
chaperone/cutil/protocol.py
chaperone/cutil/env.py
chaperone/cutil/syslog.py
chaperone/cutil/servers.py
chaperone/cutil/__init__.py
