Metadata-Version: 2.0
Name: chaperone
Version: 0.2.23
Summary: Simple system init daemon for Docker-like environments
Home-page: http://github.com/garywiz/chaperone
Author: Gary Wisniewski
Author-email: garyw@blueseastech.com
License: BSD 3
Keywords: docker init systemd syslog
Platform: UNKNOWN
Classifier: Development Status :: 4 - Beta
Classifier: Intended Audience :: Developers
Classifier: License :: OSI Approved :: Apache Software License
Classifier: Natural Language :: English
Classifier: Operating System :: POSIX :: Linux
Classifier: Programming Language :: Python :: 3
Classifier: Topic :: System :: Logging
Classifier: Topic :: System :: Boot :: Init
Requires-Dist: docopt (>=0.6.2)
Requires-Dist: setproctitle (>=1.1.8)
Requires-Dist: PyYAML (>=3.1.1)
Requires-Dist: voluptuous (>=0.8.7)
Requires-Dist: aiocron (>=0.3)
